<?xml version="1.0"?>
<Template Originator="Levi Bard" Language="Boo" Created="07/29/2010" LastModified="07/29/2010">
	<TemplateConfiguration>
		<_Name>Boo Unity Script</_Name>
		<Icon>md-unityscript-file</Icon>
		<_Category>Unity</_Category>
		<_Description>Creates a new Boo script for Unity.</_Description>
	</TemplateConfiguration>
	
	<TemplateFiles>
		<File DefaultExtension=".boo" DefaultName="NewBehaviourScript" AddStandardHeader="True">
		<![CDATA[import UnityEngine
		
class ${FileNameWithoutExtension}(MonoBehaviour):
	# Use this for initialization
	def Start ():
		pass
	
	# Update is called once per frame
	def Update ():
		pass
]]>
		</File>
	</TemplateFiles>
	
	<FileOptions/>
	
</Template>
